[
  {
    "name": "Musical Symbols",
    "questions": [
      {
        "answer": "Natural",
        "img": "ms-100",
        "disabled": false
      },
      {
        "answer": "Fortepiano",
        "img": "ms-200",
        "disabled": false
      },
      {
        "answer": "Double Sharp",
        "img": "ms-300",
        "disabled": false
      },
      {
        "answer": "Tremolo",
        "img": "ms-400",
        "disabled": false
      },
      {
        "answer": "Arpeggio",
        "img": "ms-500",
        "disabled": false
      },
      {
        "answer": "Dal Segno",
        "img": "ms-600",
        "disabled": false
      },
      {
        "answer": "Caesura",
        "img": "ms-700",
        "disabled": false
      }
    ]
  },
  {
    "name": "Time Signatures",
    "questions": [
      {
        "answer": "4/4",
        "img": "ts-100",
        "disabled": false
      },
      {
        "answer": "2/4",
        "img": "ts-200",
        "disabled": false
      },
      {
        "answer": "3/4",
        "img": "ts-300",
        "disabled": false
      },
      {
        "answer": "3/8",
        "img": "ts-400",
        "disabled": false
      },
      {
        "answer": "6/4",
        "img": "ts-500",
        "disabled": false
      },
      {
        "answer": "10/4",
        "img": "ts-600",
        "disabled": false
      },
      {
        "answer": "11/16",
        "img": "ts-700",
        "disabled": false
      }
    ]
  },
  {
    "name": "Intervals",
    "questions": [
      {
        "answer": "Perfect 8th",
        "img": "in-100",
        "disabled": false
      },
      {
        "answer": "Major 3rd",
        "img": "in-200",
        "disabled": false
      },
      {
        "answer": "Major 7th",
        "img": "in-300",
        "disabled": false
      },
      {
        "answer": "Minor 2nd",
        "img": "in-400",
        "disabled": false
      },
      {
        "answer": "Minor 7th",
        "img": "in-500",
        "disabled": false
      },
      {
        "answer": "Minor 6th",
        "img": "in-600",
        "disabled": false
      },
      {
        "answer": "Tritone",
        "img": "in-700",
        "disabled": false
      }
    ]
  }
]